{
  "bib": 116,
  "firstName": "Uwe",
  "lastName": "Hollerbach",
  "displayName": "Uwe Hollerbach",
  "activities": [
    {
      "date": "2026-05-01",
      "miles": 0.58,
      "km": 0.93,
      "type": "walk",
      "time": null,
      "comment": ""
    },
    {
      "date": "2026-05-01",
      "miles": 5.06,
      "km": 8.14,
      "type": "walk",
      "time": null,
      "comment": ""
    },
    {
      "date": "2026-05-01",
      "miles": 1.15,
      "km": 1.85,
      "type": "walk",
      "time": null,
      "comment": ""
    },
    {
      "date": "2026-05-01",
      "miles": 0.56,
      "km": 0.9,
      "type": "walk",
      "time": null,
      "comment": ""
    },
    {
      "date": "2026-05-02",
      "miles": 3.67,
      "km": 5.91,
      "type": "walk",
      "time": null,
      "comment": ""
    },
    {
      "date": "2026-05-02",
      "miles": 1.31,
      "km": 2.11,
      "type": "run",
      "time": null,
      "comment": ""
    },
    {
      "date": "2026-05-02",
      "miles": 15.16,
      "km": 24.4,
      "type": "run",
      "time": null,
      "comment": "Sweep last part of Miwok 100K! What an awesome day!"
    },
    {
      "date": "2026-05-03",
      "miles": 3.8,
      "km": 6.12,
      "type": "walk",
      "time": null,
      "comment": ""
    },
    {
      "date": "2026-05-03",
      "miles": 1.2,
      "km": 1.93,
      "type": "walk",
      "time": null,
      "comment": ""
    },
    {
      "date": "2026-05-03",
      "miles": 0.52,
      "km": 0.84,
      "type": "walk",
      "time": null,
      "comment": ""
    },
    {
      "date": "2026-05-04",
      "miles": 7.02,
      "km": 11.3,
      "type": "walk",
      "time": null,
      "comment": ""
    },
    {
      "date": "2026-05-04",
      "miles": 1.5,
      "km": 2.41,
      "type": "walk",
      "time": null,
      "comment": ""
    },
    {
      "date": "2026-05-05",
      "miles": 5.11,
      "km": 8.22,
      "type": "walk",
      "time": null,
      "comment": ""
    },
    {
      "date": "2026-05-05",
      "miles": 2.52,
      "km": 4.06,
      "type": "walk",
      "time": null,
      "comment": ""
    },
    {
      "date": "2026-05-05",
      "miles": 0.39,
      "km": 0.63,
      "type": "walk",
      "time": null,
      "comment": ""
    }
  ],
  "totalActivities": 15,
  "activeDays": 5,
  "restDays": 0
}