{
  "bib": 166,
  "firstName": "Beth",
  "lastName": "Arrisi",
  "displayName": "Beth Arrisi",
  "activities": [
    {
      "date": "2026-05-01",
      "miles": 2.0,
      "km": 3.22,
      "type": "walk",
      "time": null,
      "comment": ""
    },
    {
      "date": "2026-05-02",
      "miles": 2.5,
      "km": 4.02,
      "type": "walk",
      "time": null,
      "comment": ""
    },
    {
      "date": "2026-05-03",
      "miles": 8.3,
      "km": 13.36,
      "type": "walk",
      "time": null,
      "comment": ""
    },
    {
      "date": "2026-05-04",
      "miles": 5.8,
      "km": 9.33,
      "type": "walk",
      "time": null,
      "comment": ""
    },
    {
      "date": "2026-05-05",
      "miles": 5.6,
      "km": 9.01,
      "type": "walk",
      "time": null,
      "comment": ""
    },
    {
      "date": "2026-05-06",
      "miles": 3.0,
      "km": 4.83,
      "type": "walk",
      "time": null,
      "comment": ""
    },
    {
      "date": "2026-05-07",
      "miles": 2.0,
      "km": 3.22,
      "type": "walk",
      "time": null,
      "comment": ""
    },
    {
      "date": "2026-05-08",
      "miles": 2.0,
      "km": 3.22,
      "type": "walk",
      "time": null,
      "comment": ""
    },
    {
      "date": "2026-05-09",
      "miles": 6.6,
      "km": 10.62,
      "type": "walk",
      "time": null,
      "comment": ""
    },
    {
      "date": "2026-05-10",
      "miles": 8.6,
      "km": 13.84,
      "type": "walk",
      "time": null,
      "comment": ""
    },
    {
      "date": "2026-05-11",
      "miles": 8.75,
      "km": 14.08,
      "type": "walk",
      "time": null,
      "comment": ""
    },
    {
      "date": "2026-05-12",
      "miles": 6.6,
      "km": 10.62,
      "type": "walk",
      "time": null,
      "comment": ""
    },
    {
      "date": "2026-05-13",
      "miles": 2.0,
      "km": 3.22,
      "type": "walk",
      "time": null,
      "comment": ""
    },
    {
      "date": "2026-05-14",
      "miles": 2.5,
      "km": 4.02,
      "type": "walk",
      "time": null,
      "comment": ""
    },
    {
      "date": "2026-05-15",
      "miles": 3.5,
      "km": 5.63,
      "type": "walk",
      "time": null,
      "comment": ""
    },
    {
      "date": "2026-05-16",
      "miles": 5.85,
      "km": 9.41,
      "type": "walk",
      "time": null,
      "comment": ""
    },
    {
      "date": "2026-05-17",
      "miles": 8.0,
      "km": 12.87,
      "type": "walk",
      "time": null,
      "comment": ""
    },
    {
      "date": "2026-05-18",
      "miles": 6.8,
      "km": 10.94,
      "type": "walk",
      "time": null,
      "comment": ""
    },
    {
      "date": "2026-05-19",
      "miles": 5.3,
      "km": 8.53,
      "type": "walk",
      "time": null,
      "comment": ""
    },
    {
      "date": "2026-05-20",
      "miles": 3.0,
      "km": 4.83,
      "type": "walk",
      "time": null,
      "comment": ""
    },
    {
      "date": "2026-05-21",
      "miles": 3.5,
      "km": 5.63,
      "type": "walk",
      "time": null,
      "comment": ""
    },
    {
      "date": "2026-05-22",
      "miles": 3.0,
      "km": 4.83,
      "type": "walk",
      "time": null,
      "comment": ""
    },
    {
      "date": "2026-05-23",
      "miles": 3.6,
      "km": 5.79,
      "type": "walk",
      "time": null,
      "comment": ""
    },
    {
      "date": "2026-05-24",
      "miles": 9.4,
      "km": 15.13,
      "type": "walk",
      "time": null,
      "comment": ""
    },
    {
      "date": "2026-05-25",
      "miles": 6.54,
      "km": 10.53,
      "type": "walk",
      "time": null,
      "comment": ""
    },
    {
      "date": "2026-05-26",
      "miles": 6.5,
      "km": 10.46,
      "type": "walk",
      "time": null,
      "comment": ""
    },
    {
      "date": "2026-05-27",
      "miles": 2.0,
      "km": 3.22,
      "type": "walk",
      "time": null,
      "comment": ""
    },
    {
      "date": "2026-05-28",
      "miles": 2.0,
      "km": 3.22,
      "type": "walk",
      "time": null,
      "comment": ""
    },
    {
      "date": "2026-05-29",
      "miles": 5.5,
      "km": 8.85,
      "type": "walk",
      "time": null,
      "comment": ""
    },
    {
      "date": "2026-05-30",
      "miles": 6.35,
      "km": 10.22,
      "type": "walk",
      "time": null,
      "comment": ""
    }
  ],
  "totalActivities": 30,
  "activeDays": 30,
  "restDays": 0
}