{
  "bib": 182,
  "firstName": "Randy",
  "lastName": "Mullin",
  "displayName": "Randy Mullin",
  "activities": [
    {
      "date": "2026-05-01",
      "miles": 7.46,
      "km": 12.01,
      "type": "walk",
      "time": null,
      "comment": ""
    },
    {
      "date": "2026-05-02",
      "miles": 9.1,
      "km": 14.64,
      "type": "walk",
      "time": null,
      "comment": ""
    },
    {
      "date": "2026-05-03",
      "miles": 6.01,
      "km": 9.67,
      "type": "walk",
      "time": null,
      "comment": ""
    },
    {
      "date": "2026-05-04",
      "miles": 7.25,
      "km": 11.67,
      "type": "walk",
      "time": null,
      "comment": ""
    },
    {
      "date": "2026-05-05",
      "miles": 7.46,
      "km": 12.01,
      "type": "walk",
      "time": null,
      "comment": ""
    },
    {
      "date": "2026-05-06",
      "miles": 6.75,
      "km": 10.86,
      "type": "walk",
      "time": null,
      "comment": ""
    },
    {
      "date": "2026-05-07",
      "miles": 5.67,
      "km": 9.12,
      "type": "walk",
      "time": null,
      "comment": ""
    },
    {
      "date": "2026-05-08",
      "miles": 7.35,
      "km": 11.83,
      "type": "walk",
      "time": null,
      "comment": ""
    },
    {
      "date": "2026-05-09",
      "miles": 7.23,
      "km": 11.64,
      "type": "walk",
      "time": null,
      "comment": ""
    },
    {
      "date": "2026-05-10",
      "miles": 6.26,
      "km": 10.07,
      "type": "walk",
      "time": null,
      "comment": ""
    },
    {
      "date": "2026-05-11",
      "miles": 8.17,
      "km": 13.15,
      "type": "walk",
      "time": null,
      "comment": ""
    },
    {
      "date": "2026-05-12",
      "miles": 3.89,
      "km": 6.26,
      "type": "walk",
      "time": null,
      "comment": ""
    }
  ],
  "totalActivities": 12,
  "activeDays": 12,
  "restDays": 0
}