{
  "bib": 363,
  "firstName": "Ginger",
  "lastName": "Trimble Knox",
  "displayName": "Ginger Trimble Knox",
  "activities": [
    {
      "date": "2026-05-01",
      "miles": 3.0,
      "km": 4.83,
      "type": "run",
      "time": null,
      "comment": ""
    },
    {
      "date": "2026-05-02",
      "miles": 11.5,
      "km": 18.51,
      "type": "run",
      "time": null,
      "comment": ""
    },
    {
      "date": "2026-05-03",
      "miles": 12.0,
      "km": 19.31,
      "type": "run",
      "time": null,
      "comment": ""
    },
    {
      "date": "2026-05-04",
      "miles": 3.0,
      "km": 4.83,
      "type": "run",
      "time": null,
      "comment": ""
    },
    {
      "date": "2026-05-05",
      "miles": 6.6,
      "km": 10.62,
      "type": "run",
      "time": null,
      "comment": ""
    },
    {
      "date": "2026-05-06",
      "miles": 2.5,
      "km": 4.02,
      "type": "run",
      "time": null,
      "comment": ""
    },
    {
      "date": "2026-05-07",
      "miles": 6.5,
      "km": 10.46,
      "type": "run",
      "time": null,
      "comment": ""
    },
    {
      "date": "2026-05-08",
      "miles": 6.0,
      "km": 9.66,
      "type": "run",
      "time": null,
      "comment": ""
    },
    {
      "date": "2026-05-09",
      "miles": 3.5,
      "km": 5.63,
      "type": "run",
      "time": null,
      "comment": ""
    },
    {
      "date": "2026-05-10",
      "miles": 25.0,
      "km": 40.23,
      "type": "run",
      "time": null,
      "comment": ""
    },
    {
      "date": "2026-05-11",
      "miles": 3.1,
      "km": 4.99,
      "type": "run",
      "time": null,
      "comment": ""
    },
    {
      "date": "2026-05-12",
      "miles": 6.2,
      "km": 9.98,
      "type": "run",
      "time": null,
      "comment": ""
    },
    {
      "date": "2026-05-13",
      "miles": 3.1,
      "km": 4.99,
      "type": "run",
      "time": null,
      "comment": ""
    },
    {
      "date": "2026-05-14",
      "miles": 6.8,
      "km": 10.94,
      "type": "run",
      "time": null,
      "comment": ""
    },
    {
      "date": "2026-05-15",
      "miles": 3.5,
      "km": 5.63,
      "type": "run",
      "time": null,
      "comment": ""
    },
    {
      "date": "2026-05-16",
      "miles": 12.0,
      "km": 19.31,
      "type": "run",
      "time": null,
      "comment": ""
    },
    {
      "date": "2026-05-17",
      "miles": 12.5,
      "km": 20.12,
      "type": "run",
      "time": null,
      "comment": ""
    }
  ],
  "totalActivities": 17,
  "activeDays": 17,
  "restDays": 0
}