{
  "bib": 379,
  "firstName": "Taylor",
  "lastName": "Johnston",
  "displayName": "Taylor Johnston",
  "activities": [
    {
      "date": "2026-05-01",
      "miles": 5.5,
      "km": 8.85,
      "type": "run",
      "time": null,
      "comment": ""
    },
    {
      "date": "2026-05-02",
      "miles": 5.6,
      "km": 9.01,
      "type": "run",
      "time": null,
      "comment": ""
    },
    {
      "date": "2026-05-03",
      "miles": 0.0,
      "km": 0.0,
      "type": "rest",
      "time": null,
      "comment": ""
    },
    {
      "date": "2026-05-04",
      "miles": 7.1,
      "km": 11.43,
      "type": "run",
      "time": null,
      "comment": ""
    },
    {
      "date": "2026-05-05",
      "miles": 5.53,
      "km": 8.9,
      "type": "run",
      "time": null,
      "comment": ""
    },
    {
      "date": "2026-05-06",
      "miles": 7.0,
      "km": 11.27,
      "type": "run",
      "time": null,
      "comment": ""
    },
    {
      "date": "2026-05-07",
      "miles": 0.0,
      "km": 0.0,
      "type": "rest",
      "time": null,
      "comment": ""
    },
    {
      "date": "2026-05-08",
      "miles": 6.5,
      "km": 10.46,
      "type": "run",
      "time": null,
      "comment": ""
    },
    {
      "date": "2026-05-09",
      "miles": 3.13,
      "km": 5.04,
      "type": "run",
      "time": null,
      "comment": ""
    },
    {
      "date": "2026-05-09",
      "miles": 4.8,
      "km": 7.72,
      "type": "run",
      "time": null,
      "comment": ""
    },
    {
      "date": "2026-05-10",
      "miles": 0.0,
      "km": 0.0,
      "type": "rest",
      "time": null,
      "comment": ""
    },
    {
      "date": "2026-05-11",
      "miles": 7.14,
      "km": 11.49,
      "type": "run",
      "time": null,
      "comment": ""
    },
    {
      "date": "2026-05-12",
      "miles": 7.1,
      "km": 11.43,
      "type": "run",
      "time": null,
      "comment": ""
    },
    {
      "date": "2026-05-13",
      "miles": 8.25,
      "km": 13.28,
      "type": "run",
      "time": null,
      "comment": ""
    },
    {
      "date": "2026-05-14",
      "miles": 8.02,
      "km": 12.91,
      "type": "run",
      "time": null,
      "comment": ""
    },
    {
      "date": "2026-05-15",
      "miles": 0.0,
      "km": 0.0,
      "type": "rest",
      "time": null,
      "comment": ""
    },
    {
      "date": "2026-05-16",
      "miles": 5.17,
      "km": 8.32,
      "type": "run",
      "time": null,
      "comment": ""
    },
    {
      "date": "2026-05-17",
      "miles": 0.0,
      "km": 0.0,
      "type": "rest",
      "time": null,
      "comment": ""
    },
    {
      "date": "2026-05-18",
      "miles": 8.62,
      "km": 13.87,
      "type": "run",
      "time": null,
      "comment": ""
    },
    {
      "date": "2026-05-19",
      "miles": 0.0,
      "km": 0.0,
      "type": "rest",
      "time": null,
      "comment": ""
    },
    {
      "date": "2026-05-20",
      "miles": 10.2,
      "km": 16.42,
      "type": "run",
      "time": null,
      "comment": ""
    },
    {
      "date": "2026-05-21",
      "miles": 9.45,
      "km": 15.21,
      "type": "run",
      "time": null,
      "comment": ""
    },
    {
      "date": "2026-05-22",
      "miles": 4.02,
      "km": 6.47,
      "type": "run",
      "time": null,
      "comment": ""
    },
    {
      "date": "2026-05-23",
      "miles": 5.04,
      "km": 8.11,
      "type": "run",
      "time": null,
      "comment": ""
    },
    {
      "date": "2026-05-24",
      "miles": 0.0,
      "km": 0.0,
      "type": "rest",
      "time": null,
      "comment": ""
    },
    {
      "date": "2026-05-25",
      "miles": 0.0,
      "km": 0.0,
      "type": "rest",
      "time": null,
      "comment": ""
    },
    {
      "date": "2026-05-26",
      "miles": 0.0,
      "km": 0.0,
      "type": "rest",
      "time": null,
      "comment": ""
    },
    {
      "date": "2026-05-27",
      "miles": 10.05,
      "km": 16.17,
      "type": "run",
      "time": null,
      "comment": ""
    },
    {
      "date": "2026-05-28",
      "miles": 11.2,
      "km": 18.02,
      "type": "run",
      "time": null,
      "comment": ""
    },
    {
      "date": "2026-05-29",
      "miles": 5.57,
      "km": 8.96,
      "type": "run",
      "time": null,
      "comment": ""
    },
    {
      "date": "2026-05-30",
      "miles": 11.55,
      "km": 18.59,
      "type": "run",
      "time": null,
      "comment": ""
    },
    {
      "date": "2026-05-31",
      "miles": 0.0,
      "km": 0.0,
      "type": "rest",
      "time": null,
      "comment": ""
    },
    {
      "date": "2026-06-01",
      "miles": 8.71,
      "km": 14.02,
      "type": "run",
      "time": null,
      "comment": ""
    },
    {
      "date": "2026-06-02",
      "miles": 0.0,
      "km": 0.0,
      "type": "rest",
      "time": null,
      "comment": ""
    },
    {
      "date": "2026-06-03",
      "miles": 10.12,
      "km": 16.29,
      "type": "run",
      "time": null,
      "comment": ""
    },
    {
      "date": "2026-06-04",
      "miles": 8.33,
      "km": 13.41,
      "type": "run",
      "time": null,
      "comment": ""
    },
    {
      "date": "2026-06-05",
      "miles": 6.41,
      "km": 10.32,
      "type": "run",
      "time": null,
      "comment": ""
    },
    {
      "date": "2026-06-06",
      "miles": 5.57,
      "km": 8.96,
      "type": "run",
      "time": null,
      "comment": ""
    },
    {
      "date": "2026-06-07",
      "miles": 0.0,
      "km": 0.0,
      "type": "rest",
      "time": null,
      "comment": ""
    },
    {
      "date": "2026-06-08",
      "miles": 9.71,
      "km": 15.63,
      "type": "run",
      "time": null,
      "comment": ""
    },
    {
      "date": "2026-06-09",
      "miles": 8.02,
      "km": 12.91,
      "type": "run",
      "time": null,
      "comment": ""
    },
    {
      "date": "2026-06-10",
      "miles": 10.11,
      "km": 16.27,
      "type": "run",
      "time": null,
      "comment": ""
    },
    {
      "date": "2026-06-11",
      "miles": 6.81,
      "km": 10.96,
      "type": "run",
      "time": null,
      "comment": ""
    },
    {
      "date": "2026-06-12",
      "miles": 0.0,
      "km": 0.0,
      "type": "rest",
      "time": null,
      "comment": ""
    },
    {
      "date": "2026-06-13",
      "miles": 6.07,
      "km": 9.77,
      "type": "run",
      "time": null,
      "comment": ""
    },
    {
      "date": "2026-06-14",
      "miles": 0.0,
      "km": 0.0,
      "type": "rest",
      "time": null,
      "comment": ""
    },
    {
      "date": "2026-06-15",
      "miles": 12.34,
      "km": 19.86,
      "type": "run",
      "time": null,
      "comment": ""
    },
    {
      "date": "2026-06-16",
      "miles": 7.0,
      "km": 11.27,
      "type": "run",
      "time": null,
      "comment": ""
    },
    {
      "date": "2026-06-16",
      "miles": 5.05,
      "km": 8.13,
      "type": "run",
      "time": null,
      "comment": ""
    },
    {
      "date": "2026-06-17",
      "miles": 10.62,
      "km": 17.09,
      "type": "run",
      "time": null,
      "comment": ""
    },
    {
      "date": "2026-06-18",
      "miles": 6.75,
      "km": 10.86,
      "type": "run",
      "time": null,
      "comment": ""
    },
    {
      "date": "2026-06-19",
      "miles": 0.0,
      "km": 0.0,
      "type": "rest",
      "time": null,
      "comment": ""
    },
    {
      "date": "2026-06-20",
      "miles": 0.0,
      "km": 0.0,
      "type": "rest",
      "time": null,
      "comment": ""
    },
    {
      "date": "2026-06-21",
      "miles": 0.0,
      "km": 0.0,
      "type": "rest",
      "time": null,
      "comment": ""
    },
    {
      "date": "2026-06-22",
      "miles": 0.0,
      "km": 0.0,
      "type": "rest",
      "time": null,
      "comment": ""
    },
    {
      "date": "2026-06-23",
      "miles": 7.56,
      "km": 12.17,
      "type": "run",
      "time": null,
      "comment": ""
    },
    {
      "date": "2026-06-24",
      "miles": 8.67,
      "km": 13.95,
      "type": "run",
      "time": null,
      "comment": ""
    },
    {
      "date": "2026-06-25",
      "miles": 0.0,
      "km": 0.0,
      "type": "rest",
      "time": null,
      "comment": ""
    },
    {
      "date": "2026-06-26",
      "miles": 0.0,
      "km": 0.0,
      "type": "rest",
      "time": null,
      "comment": ""
    },
    {
      "date": "2026-06-27",
      "miles": 0.0,
      "km": 0.0,
      "type": "rest",
      "time": null,
      "comment": ""
    },
    {
      "date": "2026-06-28",
      "miles": 0.0,
      "km": 0.0,
      "type": "rest",
      "time": null,
      "comment": ""
    },
    {
      "date": "2026-06-29",
      "miles": 0.0,
      "km": 0.0,
      "type": "rest",
      "time": null,
      "comment": ""
    },
    {
      "date": "2026-06-30",
      "miles": 0.0,
      "km": 0.0,
      "type": "rest",
      "time": null,
      "comment": ""
    },
    {
      "date": "2026-07-01",
      "miles": 0.0,
      "km": 0.0,
      "type": "rest",
      "time": null,
      "comment": ""
    },
    {
      "date": "2026-07-02",
      "miles": 0.0,
      "km": 0.0,
      "type": "rest",
      "time": null,
      "comment": ""
    },
    {
      "date": "2026-07-03",
      "miles": 0.0,
      "km": 0.0,
      "type": "rest",
      "time": null,
      "comment": ""
    },
    {
      "date": "2026-07-04",
      "miles": 0.0,
      "km": 0.0,
      "type": "rest",
      "time": null,
      "comment": ""
    },
    {
      "date": "2026-07-05",
      "miles": 0.0,
      "km": 0.0,
      "type": "rest",
      "time": null,
      "comment": ""
    },
    {
      "date": "2026-07-06",
      "miles": 0.0,
      "km": 0.0,
      "type": "rest",
      "time": null,
      "comment": ""
    },
    {
      "date": "2026-07-07",
      "miles": 6.02,
      "km": 9.69,
      "type": "run",
      "time": null,
      "comment": ""
    },
    {
      "date": "2026-07-08",
      "miles": 0.0,
      "km": 0.0,
      "type": "rest",
      "time": null,
      "comment": ""
    }
  ],
  "totalActivities": 40,
  "activeDays": 38,
  "restDays": 31
}