{
  "bib": 43,
  "firstName": "Philip",
  "lastName": "Lee",
  "displayName": "Philip Lee",
  "activities": [
    {
      "date": "2026-05-01",
      "miles": 13.1,
      "km": 21.08,
      "type": "run",
      "time": null,
      "comment": ""
    },
    {
      "date": "2026-05-02",
      "miles": 5.0,
      "km": 8.05,
      "type": "run",
      "time": null,
      "comment": ""
    },
    {
      "date": "2026-05-03",
      "miles": 3.0,
      "km": 4.83,
      "type": "run",
      "time": null,
      "comment": ""
    },
    {
      "date": "2026-05-04",
      "miles": 7.0,
      "km": 11.27,
      "type": "run",
      "time": null,
      "comment": ""
    },
    {
      "date": "2026-05-05",
      "miles": 4.0,
      "km": 6.44,
      "type": "run",
      "time": null,
      "comment": ""
    },
    {
      "date": "2026-05-06",
      "miles": 5.0,
      "km": 8.05,
      "type": "run",
      "time": null,
      "comment": ""
    },
    {
      "date": "2026-05-07",
      "miles": 11.5,
      "km": 18.51,
      "type": "run",
      "time": null,
      "comment": ""
    },
    {
      "date": "2026-05-08",
      "miles": 5.0,
      "km": 8.05,
      "type": "run",
      "time": null,
      "comment": ""
    },
    {
      "date": "2026-05-09",
      "miles": 4.0,
      "km": 6.44,
      "type": "run",
      "time": null,
      "comment": ""
    },
    {
      "date": "2026-05-10",
      "miles": 4.19,
      "km": 6.74,
      "type": "run",
      "time": null,
      "comment": ""
    },
    {
      "date": "2026-05-11",
      "miles": 3.0,
      "km": 4.83,
      "type": "run",
      "time": null,
      "comment": ""
    },
    {
      "date": "2026-05-12",
      "miles": 3.0,
      "km": 4.83,
      "type": "run",
      "time": null,
      "comment": ""
    },
    {
      "date": "2026-05-13",
      "miles": 3.0,
      "km": 4.83,
      "type": "run",
      "time": null,
      "comment": ""
    },
    {
      "date": "2026-05-14",
      "miles": 31.5,
      "km": 50.69,
      "type": "run",
      "time": null,
      "comment": ""
    },
    {
      "date": "2026-05-15",
      "miles": 3.0,
      "km": 4.83,
      "type": "run",
      "time": null,
      "comment": ""
    },
    {
      "date": "2026-05-16",
      "miles": 3.0,
      "km": 4.83,
      "type": "run",
      "time": null,
      "comment": ""
    },
    {
      "date": "2026-05-17",
      "miles": 3.64,
      "km": 5.86,
      "type": "run",
      "time": null,
      "comment": ""
    },
    {
      "date": "2026-05-18",
      "miles": 7.0,
      "km": 11.27,
      "type": "run",
      "time": null,
      "comment": ""
    },
    {
      "date": "2026-05-19",
      "miles": 5.0,
      "km": 8.05,
      "type": "run",
      "time": null,
      "comment": ""
    },
    {
      "date": "2026-05-20",
      "miles": 5.0,
      "km": 8.05,
      "type": "run",
      "time": null,
      "comment": ""
    },
    {
      "date": "2026-05-21",
      "miles": 10.27,
      "km": 16.53,
      "type": "run",
      "time": null,
      "comment": ""
    },
    {
      "date": "2026-05-22",
      "miles": 12.0,
      "km": 19.31,
      "type": "run",
      "time": null,
      "comment": ""
    },
    {
      "date": "2026-05-23",
      "miles": 6.0,
      "km": 9.66,
      "type": "run",
      "time": null,
      "comment": ""
    },
    {
      "date": "2026-05-24",
      "miles": 5.0,
      "km": 8.05,
      "type": "run",
      "time": null,
      "comment": ""
    },
    {
      "date": "2026-05-25",
      "miles": 5.11,
      "km": 8.22,
      "type": "run",
      "time": null,
      "comment": ""
    },
    {
      "date": "2026-05-26",
      "miles": 5.0,
      "km": 8.05,
      "type": "run",
      "time": null,
      "comment": ""
    },
    {
      "date": "2026-05-27",
      "miles": 4.25,
      "km": 6.84,
      "type": "run",
      "time": null,
      "comment": ""
    },
    {
      "date": "2026-05-28",
      "miles": 15.28,
      "km": 24.59,
      "type": "run",
      "time": null,
      "comment": ""
    },
    {
      "date": "2026-05-29",
      "miles": 9.85,
      "km": 15.85,
      "type": "run",
      "time": null,
      "comment": ""
    },
    {
      "date": "2026-05-30",
      "miles": 5.0,
      "km": 8.05,
      "type": "run",
      "time": null,
      "comment": ""
    },
    {
      "date": "2026-05-31",
      "miles": 5.0,
      "km": 8.05,
      "type": "run",
      "time": null,
      "comment": ""
    },
    {
      "date": "2026-06-01",
      "miles": 5.0,
      "km": 8.05,
      "type": "run",
      "time": null,
      "comment": ""
    },
    {
      "date": "2026-06-02",
      "miles": 9.14,
      "km": 14.71,
      "type": "run",
      "time": null,
      "comment": ""
    },
    {
      "date": "2026-06-03",
      "miles": 5.13,
      "km": 8.26,
      "type": "run",
      "time": null,
      "comment": ""
    },
    {
      "date": "2026-06-04",
      "miles": 16.8,
      "km": 27.04,
      "type": "run",
      "time": null,
      "comment": ""
    }
  ],
  "totalActivities": 35,
  "activeDays": 35,
  "restDays": 0
}