{
  "bib": 47,
  "firstName": "Michael",
  "lastName": "DeLang",
  "displayName": "Michael DeLang",
  "activities": [
    {
      "date": "2026-05-01",
      "miles": 4.06,
      "km": 6.53,
      "type": "walk",
      "time": null,
      "comment": ""
    },
    {
      "date": "2026-05-01",
      "miles": 1.72,
      "km": 2.77,
      "type": "walk",
      "time": null,
      "comment": ""
    },
    {
      "date": "2026-05-02",
      "miles": 4.07,
      "km": 6.55,
      "type": "walk",
      "time": null,
      "comment": ""
    },
    {
      "date": "2026-05-03",
      "miles": 1.38,
      "km": 2.22,
      "type": "walk",
      "time": null,
      "comment": ""
    },
    {
      "date": "2026-05-03",
      "miles": 2.33,
      "km": 3.75,
      "type": "walk",
      "time": null,
      "comment": ""
    },
    {
      "date": "2026-05-04",
      "miles": 5.72,
      "km": 9.21,
      "type": "walk",
      "time": null,
      "comment": ""
    },
    {
      "date": "2026-05-04",
      "miles": 2.07,
      "km": 3.33,
      "type": "walk",
      "time": null,
      "comment": ""
    },
    {
      "date": "2026-05-05",
      "miles": 3.72,
      "km": 5.99,
      "type": "walk",
      "time": null,
      "comment": ""
    },
    {
      "date": "2026-05-06",
      "miles": 5.39,
      "km": 8.67,
      "type": "walk",
      "time": null,
      "comment": ""
    },
    {
      "date": "2026-05-06",
      "miles": 4.04,
      "km": 6.5,
      "type": "walk",
      "time": null,
      "comment": ""
    },
    {
      "date": "2026-05-07",
      "miles": 6.38,
      "km": 10.27,
      "type": "walk",
      "time": null,
      "comment": ""
    }
  ],
  "totalActivities": 11,
  "activeDays": 7,
  "restDays": 0
}